jsonschema/__init__.py
jsonschema/__main__.py
jsonschema/_format.py
jsonschema/_legacy_validators.py
jsonschema/_reflect.py
jsonschema/_types.py
jsonschema/_utils.py
jsonschema/_validators.py
jsonschema/cli.py
jsonschema/compat.py
jsonschema/exceptions.py
jsonschema/validators.py
jsonschema/benchmarks/__init__.py
jsonschema/benchmarks/issue232.py
jsonschema/benchmarks/json_schema_test_suite.py
jsonschema/schemas/draft3.json
jsonschema/schemas/draft4.json
jsonschema/schemas/draft6.json
jsonschema/schemas/draft7-codelane.json
jsonschema/schemas/draft7.json
jsonschema/tests/__init__.py
jsonschema/tests/_helpers.py
jsonschema/tests/_suite.py
jsonschema/tests/helpers.py
jsonschema/tests/test_cli.py
jsonschema/tests/test_exceptions.py
jsonschema/tests/test_format.py
jsonschema/tests/test_jsonschema_test_suite.py
jsonschema/tests/test_types.py
jsonschema/tests/test_validators.py
jsonschema_codelane-3.1.2b2.dist-info/COPYING
jsonschema_codelane-3.1.2b2.dist-info/METADATA
jsonschema_codelane-3.1.2b2.dist-info/WHEEL
jsonschema_codelane-3.1.2b2.dist-info/entry_points.txt
jsonschema_codelane-3.1.2b2.dist-info/top_level.txt
jsonschema_codelane-3.1.2b2.dist-info/RECORD
