Metadata-Version: 2.1
Name: jsonschema-codelane
Version: 3.1.2b2
Summary: An implementation of JSON Schema validation for Python
Home-page: https://github.com/codelane/jsonschema
Author: Julian Berman
Author-email: Julian@GrayVines.com
License: UNKNOWN
Project-URL: Docs, https://python-jsonschema.readthedocs.io/en/latest/
Platform: UNKNOWN
Classifier: Development Status :: 5 - Production/Stable
Classifier: Intended Audience :: Developers
Classifier: License :: OSI Approved :: MIT License
Classifier: Operating System :: OS Independent
Classifier: Programming Language :: Python
Classifier: Programming Language :: Python :: 2
Classifier: Programming Language :: Python :: 2.7
Classifier: Programming Language :: Python :: 3
Classifier: Programming Language :: Python :: 3.5
Classifier: Programming Language :: Python :: 3.6
Classifier: Programming Language :: Python :: 3.7
Classifier: Programming Language :: Python :: 3.8
Classifier: Programming Language :: Python :: Implementation :: CPython
Classifier: Programming Language :: Python :: Implementation :: PyPy
Requires-Dist: attrs (>=17.4.0)
Requires-Dist: importlib-metadata
Requires-Dist: pyrsistent (>=0.14.0)
Requires-Dist: setuptools
Requires-Dist: six (>=1.11.0)
Requires-Dist: jsonpointer (>=2.0)
Requires-Dist: functools32 ; python_version < "3"
Provides-Extra: format
Requires-Dist: idna ; extra == 'format'
Requires-Dist: rfc3987 ; extra == 'format'
Requires-Dist: strict-rfc3339 ; extra == 'format'
Requires-Dist: webcolors ; extra == 'format'
